gstnumcheck/__init__.py
gstnumcheck/gst.py
gstnumcheck/tempCodeRunnerFile.py
checkgstnum-0.0.1.dist-info/LICENCE
checkgstnum-0.0.1.dist-info/METADATA
checkgstnum-0.0.1.dist-info/WHEEL
checkgstnum-0.0.1.dist-info/top_level.txt
checkgstnum-0.0.1.dist-info/RECORD
